pytest_pythonpath.py
pytest_pythonpath-0.7.4.dist-info/LICENSE.txt
pytest_pythonpath-0.7.4.dist-info/METADATA
pytest_pythonpath-0.7.4.dist-info/WHEEL
pytest_pythonpath-0.7.4.dist-info/entry_points.txt
pytest_pythonpath-0.7.4.dist-info/top_level.txt
pytest_pythonpath-0.7.4.dist-info/RECORD
